<?xml version="1.0" encoding="utf-8"?>
<newsMessage xmlns="http://iptc.org/std/nar/2006-10-01/">
  <header>
    <sent>2023-08-29T08:37:14+02:00</sent>
  </header>

  <itemSet>
    <newsItem xmlns:xsi="http://www.w3.org/2001/XMLSchema-instance" xsi:schemaLocation="http://iptc.org/std/nar/2006-10-01/" standard="NewsML-G2" standardversion="2.28" conformance="power" xml:lang="it" guid="urn:newsml:keystone-sda.ch:20230829:20230829083714647157461770142" version="1">
      <catalogRef href="http://www.iptc.org/std/catalog/catalog.IPTC-G2-Standards_34.xml"/>
      <catalogRef href="http://www.keystone-sda.ch/NewsML_G2/SDA-G2-Catalog.xml"/>

      <itemMeta>
        <itemClass qcode="ninat:text"/>
        <provider qcode="nprov:KSDA">
           <name>sda</name>
        </provider>
        <versionCreated>2023-08-29T08:37:14+02:00</versionCreated>
        <pubStatus qcode="stat:withheld"/>
        <generator versioninfo="0.3.4">XML::NewsML_G2</generator>
        <service qcode="sdasvc:bsi"></service>
        <edNote role="sdanote:note">Questa notizia è stata generata automaticamente in base ai dati dell'Ufficio federale di statistica (UST) e riletta prima della diffusione. </edNote>
        <edNote role="sdalena:memo">Dies ist ein Test</edNote>
        
      </itemMeta>

      <contentMeta>
        <urgency>3</urgency>
        <contentCreated>2023-08-29T08:37:14+02:00</contentCreated>
        <creator>
          <name>sda-robot</name>
        </creator>
        <altId>647157461770142</altId>
        <dateline>Zurigo</dateline>
        <language tag="it"/>
        <genre qcode="sdagenre:RES">
        </genre>

        <!--storytypes-->
        <subject type="cpnat:abstract" qcode="sdastorytype:tble"></subject>
        
        <!--media topics-->
        <subject type="cpnat:abstract" qcode="sdamarschannel:ELE"></subject>
<subject type="cpnat:abstract" qcode="sdamarschannel:LOH"></subject>
<subject type="cpnat:abstract" qcode="sdamarschannel:PRT"></subject>

        <!--locations-->
        <located type="loctype:city" qcode="sdamarsgeo:CH">
<name>Schweiz</name>
</located>
  
        <slugline>Federali 2023 - ZH CN</slugline>
        <headline>***TEST***La ripartizione dei 36 seggi nel canton Zurigo</headline>
        <description role="drol:teaser"> </description>
        <description role="drol:catchline"></description>
      </contentMeta>

      <contentSet>
        <inlineXML contenttype="application/xhtml+xml">
          <html xmlns="http://www.w3.org/1999/xhtml">
            <head>
              <title>***TEST***La ripartizione dei 36 seggi nel canton Zurigo</title>
            </head>
            <body>
              <p class="lead"> </p>
              <p class="paragraph">Nel canton Zurigo hanno guadagnato seggi il PVL (+3) e i Verdi (+3). Hanno perso seggi il UDC (-2), il PS (-2), il Centro (-1) e il PBD (-1).</p>
<p class="paragraph">I risultati delle elezioni al Consiglio nazionale nel canton Zurigo:</p>
<table><tbody><tr><td></td><td>numero di seggi</td><td>variazione rispetto al 2019</td><td>percentuali di voto</td><td>variazione rispetto al 2019</td></tr><tr><td>UDC</td><td>10</td><td>-2</td><td>26,7%</td><td>-4,0</td></tr><tr><td>PS</td><td>7</td><td>-2</td><td>17,3%</td><td>-4,1</td></tr><tr><td>PVL</td><td>6</td><td>+3</td><td>14,0%</td><td>+5,8</td></tr><tr><td>Verdi</td><td>5</td><td>+3</td><td>14,1%</td><td>+7,2</td></tr><tr><td>PLR</td><td>5</td><td>-</td><td>13,7%</td><td>-1,7</td></tr><tr><td>Centro</td><td>1</td><td>-1</td><td>4,4%</td><td>+0,2</td></tr><tr><td>PEV</td><td>1</td><td>-</td><td>3,3%</td><td>+0,2</td></tr><tr><td>PBD</td><td>0</td><td>-1</td><td>1,6%</td><td>-2,0</td></tr></tbody></table>
<p class="paragraph">Numero di seggi 2023: 36. Il cantone conta un seggio in più rispetto al 2019. </p>
<p class="paragraph">Tutti i partiti che hanno ottenuto almeno il 3% sono stati presi in considerazione. </p>

            </body>
          </html>
        </inlineXML>
      </contentSet>
    </newsItem>
  </itemSet>
</newsMessage>
